Metadata-Version: 2.1
Name: rucodinger
Version: 2.0.0
Summary: Main RuCodinger package
Author: RuCodinger
Author-email: rucodinger@gmail.com
